CHANGELOG.md
LICENSE
process_executor/__init__.py
process_executor/app.py
process_executor/cli.py
process_executor/const.py
process_executor/errors.py
process_executor/executor.py
process_executor/git_tools/__init__.py
process_executor/git_tools/servise.py
process_executor/main.py
process_executor/resources.py
process_executor/service.py
process_executor/settings.py
process_executor/venv_tools/__init__.py
process_executor/venv_tools/service.py
README.md
process_executor-0.0.1.dist-info/entry_points.txt
process_executor-0.0.1.dist-info/LICENSE
process_executor-0.0.1.dist-info/WHEEL
process_executor-0.0.1.dist-info/METADATA
process_executor-0.0.1.dist-info/RECORD
